{
    "name": "new monster adventure(multiplayer by maya)",
    "description": "",
    "dependencies": {
        "device": "*"
    },
    "files": [
        "main.blocks",
        "main.ts",
        "README.md",
        "assets.json",
        "tilemap.g.jres",
        "tilemap.g.ts",
        "images.g.jres",
        "images.g.ts"
    ],
    "testFiles": [
        "test.ts"
    ],
    "targetVersions": {
        "branch": "v2.0.48",
        "tag": "v2.0.48",
        "commits": "https://github.com/microsoft/pxt-arcade/commits/cb1bfd53862604a2129aba2eff909d3bec8826ed",
        "target": "2.0.48",
        "pxt": "11.3.51",
        "targetId": "arcade"
    },
    "supportedTargets": [
        "arcade"
    ],
    "preferredEditor": "blocksprj"
}
